dqlitepy/__init__.py
dqlitepy/_ffi.py
dqlitepy/client.py
dqlitepy/dbapi.py
dqlitepy/exceptions.py
dqlitepy/node.py
dqlitepy/sqlalchemy.py
dqlitepy/_lib/linux-amd64/.gitkeep
dqlitepy/_lib/linux-amd64/libdqlitepy.h
dqlitepy/_lib/linux-amd64/libsqlite3.so.0
dqlitepy/_lib/linux-amd64/libuv.so.1
dqlitepy-0.1.0.dist-info/METADATA
dqlitepy-0.1.0.dist-info/WHEEL
dqlitepy-0.1.0.dist-info/licenses/LICENSE
dqlitepy-0.1.0.dist-info/RECORD
