Metadata-Version: 2.4
Name: dqlitepy
Version: 0.1.0
Summary: Python bindings for the Canonical dqlite distributed SQLite engine
Author: VantageCompute
License: Apache-2.0
License-File: LICENSE
Keywords: bindings,distributed,dqlite,raft,sqlite
Classifier: License :: OSI Approved :: Apache Software License
Classifier: Programming Language :: Python :: 3
Classifier: Programming Language :: Python :: 3.12
Classifier: Topic :: Database
Classifier: Topic :: Software Development :: Libraries :: Python Modules
Requires-Python: >=3.12
Requires-Dist: cffi>=1.15
Requires-Dist: sqlalchemy>=2.0.44
Provides-Extra: dev
Requires-Dist: codespell; extra == 'dev'
Requires-Dist: coverage[toml]~=7.8; extra == 'dev'
Requires-Dist: pyright; extra == 'dev'
Requires-Dist: pytest-mock~=3.14; extra == 'dev'
Requires-Dist: pytest-order~=1.3; extra == 'dev'
Requires-Dist: pytest~=8.3; extra == 'dev'
Requires-Dist: python-dotenv~=1.0; extra == 'dev'
Requires-Dist: ruff; extra == 'dev'
